kitedb/__init__.py
kitedb/_kitedb.cpython-313-darwin.so
kitedb/_kitedb.pyi
kitedb/builders.py
kitedb/fluent.py
kitedb/schema.py
kitedb/traversal.py
kitedb/vector_index.py
kitedb-0.2.6.dist-info/METADATA
kitedb-0.2.6.dist-info/WHEEL
kitedb-0.2.6.dist-info/licenses/LICENSE
kitedb-0.2.6.dist-info/RECORD
