Metadata-Version: 2.4
Name: kitedb
Version: 0.2.6
Classifier: Development Status :: 4 - Beta
Classifier: Intended Audience :: Developers
Classifier: License :: OSI Approved :: MIT License
Classifier: Programming Language :: Python :: 3
Classifier: Programming Language :: Python :: 3.8
Classifier: Programming Language :: Python :: 3.9
Classifier: Programming Language :: Python :: 3.10
Classifier: Programming Language :: Python :: 3.11
Classifier: Programming Language :: Python :: 3.12
Classifier: Programming Language :: Rust
Classifier: Topic :: Database
Classifier: Topic :: Database :: Database Engines/Servers
Classifier: Topic :: Scientific/Engineering :: Artificial Intelligence
Requires-Dist: pytest>=7.0 ; extra == 'dev'
Requires-Dist: pytest-benchmark>=4.0 ; extra == 'dev'
Requires-Dist: numpy>=1.20 ; extra == 'dev'
Requires-Dist: numpy>=1.20 ; extra == 'numpy'
Provides-Extra: dev
Provides-Extra: numpy
License-File: LICENSE
Summary: High-performance embedded graph database with vector search
Keywords: graph,database,embedded,vector,search,pathfinding
Home-Page: https://github.com/mask-software/kitedb
Author: KiteDB Contributors
License: MIT
Requires-Python: >=3.8
Project-URL: Documentation, https://github.com/mask-software/kitedb#readme
Project-URL: Homepage, https://github.com/mask-software/kitedb
Project-URL: Repository, https://github.com/mask-software/kitedb
